bopen/__init__.py
bopen/__main__.py
bopen/bookmarks.py
bopen/bopen.py
bopen/make_aliases.py
bopen/open_commands.py
bopen/os_helpers.py
bopen-0.1.1.dev1.dist-info/LICENSE
bopen-0.1.1.dev1.dist-info/METADATA
bopen-0.1.1.dev1.dist-info/WHEEL
bopen-0.1.1.dev1.dist-info/entry_points.txt
bopen-0.1.1.dev1.dist-info/top_level.txt
bopen-0.1.1.dev1.dist-info/RECORD
